realmath.py
realmath-1.1.dist-info/licenses/LICENSE.txt
realmath-1.1.dist-info/METADATA
realmath-1.1.dist-info/WHEEL
realmath-1.1.dist-info/top_level.txt
realmath-1.1.dist-info/RECORD
