Metadata-Version: 2.4
Name: realmath
Version: 1.1
Summary: A humanized math library
Author: Benyamin Ghaem
Requires-Python: >=3.7
License-File: LICENSE.txt
Dynamic: license-file
